benchmark/__init__.py
benchmark/run.py
benchmark/1966_nba_draft/__init__.py
benchmark/1966_nba_draft/load.py
benchmark/financials/__init__.py
benchmark/financials/load.py
benchmark/national_parks/__init__.py
benchmark/national_parks/load.py
benchmark/rugby/__init__.py
benchmark/rugby/load.py
blendsql/__init__.py
blendsql/blendsql.py
blendsql/configure.py
blendsql/smoothie.py
blendsql/visualize.py
blendsql/common/__init__.py
blendsql/common/constants.py
blendsql/common/exceptions.py
blendsql/common/logger.py
blendsql/common/typing.py
blendsql/common/utils.py
blendsql/db/__init__.py
blendsql/db/bridge_content_encoder.py
blendsql/db/database.py
blendsql/db/duckdb.py
blendsql/db/pandas.py
blendsql/db/postgresql.py
blendsql/db/sqlalchemy.py
blendsql/db/sqlite.py
blendsql/db/utils.py
blendsql/grammars/__init__.py
blendsql/grammars/utils.py
blendsql/grammars/minEarley/__init__.py
blendsql/grammars/minEarley/earley.py
blendsql/grammars/minEarley/earley_analyzer.py
blendsql/grammars/minEarley/earley_exceptions.py
blendsql/grammars/minEarley/earley_forest.py
blendsql/grammars/minEarley/parser.py
blendsql/grammars/minEarley/tree.py
blendsql/grammars/minEarley/utils.py
blendsql/ingredients/__init__.py
blendsql/ingredients/few_shot.py
blendsql/ingredients/ingredient.py
blendsql/ingredients/utils.py
blendsql/ingredients/builtin/__init__.py
blendsql/ingredients/builtin/join/__init__.py
blendsql/ingredients/builtin/join/default_examples.json
blendsql/ingredients/builtin/join/examples.py
blendsql/ingredients/builtin/join/main.py
blendsql/ingredients/builtin/map/__init__.py
blendsql/ingredients/builtin/map/default_examples.json
blendsql/ingredients/builtin/map/examples.py
blendsql/ingredients/builtin/map/main.py
blendsql/ingredients/builtin/qa/__init__.py
blendsql/ingredients/builtin/qa/default_examples.json
blendsql/ingredients/builtin/qa/examples.py
blendsql/ingredients/builtin/qa/main.py
blendsql/ingredients/builtin/vqa/__init__.py
blendsql/ingredients/builtin/vqa/main.py
blendsql-0.1.1.dist-info/licenses/LICENSE
blendsql-0.1.1.dist-info/METADATA
blendsql-0.1.1.dist-info/WHEEL
blendsql-0.1.1.dist-info/top_level.txt
blendsql-0.1.1.dist-info/RECORD
