Metadata-Version: 2.4
Name: blendsql
Version: 0.1.1
Summary: Query language for blending SQL and LLMs across structured + unstructured data, with type constraints. 
Author-email: Parker Glenn <parkervg5@gmail.com>
License: Apache-2.0
Project-URL: Documentation, https://parkervg.github.io/blendsql/
Keywords: language models,query language,symbolic ai,sql
Classifier: Development Status :: 4 - Beta
Classifier: Intended Audience :: Developers
Classifier: Intended Audience :: Science/Research
Classifier: Topic :: Scientific/Engineering :: Artificial Intelligence
Classifier: Topic :: Text Processing
Classifier: Programming Language :: Python :: 3
Requires-Python: >=3.10
License-File: LICENSE
Requires-Dist: guidance>0.1.16
Requires-Dist: transformers>4.47.0
Requires-Dist: litellm
Requires-Dist: polars[pyarrow]
Requires-Dist: pandas>=2.0.0
Requires-Dist: bottleneck>=1.3.6
Requires-Dist: python-dotenv==1.0.1
Requires-Dist: sqlglot[rs]>=28.1.0
Requires-Dist: sqlalchemy>=2.0.0
Requires-Dist: skrub
Requires-Dist: duckdb>=1.4.3
Requires-Dist: rapidfuzz
Requires-Dist: sentence_transformers
Requires-Dist: platformdirs
Requires-Dist: tqdm
Requires-Dist: typeguard
Requires-Dist: httpx
Requires-Dist: setuptools
Requires-Dist: bm25s
Requires-Dist: diskcache
Requires-Dist: rich
Provides-Extra: test
Requires-Dist: pytest; extra == "test"
Provides-Extra: docs
Requires-Dist: mkdocs; extra == "docs"
Requires-Dist: mkdocs-material; extra == "docs"
Requires-Dist: mkdocstrings; extra == "docs"
Requires-Dist: mkdocs-section-index; extra == "docs"
Requires-Dist: mkdocstrings-python; extra == "docs"
Requires-Dist: mkdocs-jupyter; extra == "docs"
Dynamic: license-file
